b62/__init__.py
b62/b62.cpython-313-x86_64-linux-gnu.so
b62-1.1.5.dist-info/METADATA
b62-1.1.5.dist-info/WHEEL
b62-1.1.5.dist-info/licenses/LICENSE
b62-1.1.5.dist-info/RECORD
