Metadata-Version: 2.4
Name: b62
Version: 1.1.5
Classifier: Development Status :: 5 - Production/Stable
Classifier: Intended Audience :: Developers
Classifier: License :: OSI Approved :: MIT License
Classifier: Operating System :: OS Independent
Classifier: Programming Language :: Python :: 3
Classifier: Programming Language :: Python :: 3.12
Classifier: Programming Language :: Python :: 3.13
Classifier: Programming Language :: Python :: 3.14
Classifier: Programming Language :: Rust
Classifier: Topic :: Software Development :: Libraries :: Python Modules
Classifier: Topic :: Text Processing :: General
Classifier: Typing :: Typed
License-File: LICENSE
Summary: A lightning-fast, zero-dependency Base62 encoder/decoder for Python
Keywords: base62,encoding,decoding,url-shortening,performance
Author-email: Maksim Smirnov <smirnoffmg@gmail.com>
License: MIT
Requires-Python: >=3.12
Project-URL: Documentation, https://github.com/smirnoffmg/b62#readme
Project-URL: Homepage, https://github.com/smirnoffmg/b62
Project-URL: Issues, https://github.com/smirnoffmg/b62/issues
Project-URL: Repository, https://github.com/smirnoffmg/b62.git
